{
	"backtraceGraph" : 
	{
		"commands" : 
		[
			"install",
			"include"
		],
		"files" : 
		[
			"cmake-build-debug/_deps/cccl-src/cmake/CCCLInstallRules.cmake",
			"cmake-build-debug/_deps/cccl-src/CMakeLists.txt"
		],
		"nodes" : 
		[
			{
				"file" : 1
			},
			{
				"command" : 1,
				"file" : 1,
				"line" : 22,
				"parent" : 0
			},
			{
				"file" : 0,
				"parent" : 1
			},
			{
				"command" : 0,
				"file" : 0,
				"line" : 7,
				"parent" : 2
			}
		]
	},
	"installers" : 
	[
		{
			"backtrace" : 3,
			"component" : "Unspecified",
			"destination" : "lib/cmake/",
			"paths" : 
			[
				"cmake-build-debug/_deps/cccl-src/lib/cmake/cccl"
			],
			"type" : "directory"
		}
	],
	"paths" : 
	{
		"build" : "_deps/cccl-build",
		"source" : "cmake-build-debug/_deps/cccl-src"
	}
}
